scikit_hep-2025.9.1.dist-info/licenses/LICENSE
skhep/__init__.py
skhep/_show_versions.py
skhep/_version.py
scikit_hep-2025.9.1.dist-info/METADATA
scikit_hep-2025.9.1.dist-info/WHEEL
scikit_hep-2025.9.1.dist-info/top_level.txt
scikit_hep-2025.9.1.dist-info/RECORD
