Metadata-Version: 2.4
Name: scikit-hep
Version: 2025.9.1
Summary: Metapackage of Scikit-HEP project libraries for Particle Physics.
Author-email: the scikit-hep admins <scikit-hep-admins@googlegroups.com>
License: BSD 3-Clause License
Project-URL: Homepage, https://github.com/scikit-hep/scikit-hep/
Classifier: Development Status :: 4 - Beta
Classifier: Intended Audience :: Developers
Classifier: Intended Audience :: Science/Research
Classifier: Operating System :: MacOS
Classifier: Operating System :: POSIX
Classifier: Operating System :: Unix
Classifier: Programming Language :: C++
Classifier: Programming Language :: Cython
Classifier: Programming Language :: Python
Classifier: Programming Language :: Python :: 3
Classifier: Programming Language :: Python :: 3.9
Classifier: Programming Language :: Python :: 3.10
Classifier: Programming Language :: Python :: 3.11
Classifier: Programming Language :: Python :: 3.12
Classifier: Programming Language :: Python :: 3.13
Classifier: Topic :: Scientific/Engineering
Classifier: Topic :: Software Development
Classifier: Topic :: Utilities
Requires-Python: >=3.9
License-File: LICENSE
Requires-Dist: awkward~=2.8.0
Requires-Dist: decaylanguage~=0.20.0
Requires-Dist: hepstats~=0.9.0
Requires-Dist: hepunits~=2.3.0
Requires-Dist: hist~=2.9.0
Requires-Dist: histoprint~=2.6.0
Requires-Dist: iminuit~=2.31.0
Requires-Dist: matplotlib>3.4.0
Requires-Dist: mplhep~=0.4.0
Requires-Dist: numpy>=1.13.1
Requires-Dist: particle~=0.25.0
Requires-Dist: pylhe~=0.9.0
Requires-Dist: resample~=1.10.0
Requires-Dist: uproot~=5.6.0
Requires-Dist: vector~=1.6.0
Provides-Extra: test
Requires-Dist: pytest>=7.0; extra == "test"
Dynamic: license-file
